{
  "9": {
    "inputs": {
      "filename_prefix": "final_output",
      "images": [
        "33",
        0
      ]
    },
    "class_type": "SaveImage"
  },
  "13": {
    "inputs": {
      "image": "example.png",
      "choose file to upload": "image"
    },
    "class_type": "LoadImage"
  },
  "23": {
    "inputs": {
      "model_name": "8x_NMKD-Superscale_150000_G.pth"
    },
    "class_type": "Upscale Model Loader"
  },
  "24": {
    "inputs": {
      "upscale_model": [
        "23",
        0
      ],
      "image": [
        "13",
        0
      ]
    },
    "class_type": "ImageUpscaleWithModel"
  },
  "33": {
    "inputs": {
      "upscale_method": "lanczos",
      "scale_by": 0.25,
      "image": [
        "24",
        0
      ]
    },
    "class_type": "ImageScaleBy"
  }
}